{"mostUsedCharacters":[{"code":"nahida","use":0.8291},{"code":"zhongli","use":0.764},{"code":"bennett","use":0.7318},{"code":"kazuha","use":0.6668},{"code":"yelan","use":0.6365},{"code":"raiden-shogun","use":0.6344},{"code":"xingqiu","use":0.6217},{"code":"alhaitham","use":0.5616},{"code":"kokomi","use":0.5469},{"code":"xiangling","use":0.4502},{"code":"nilou","use":0.4429},{"code":"yae-miko","use":0.4076},{"code":"kuki-shinobu","use":0.3462},{"code":"hu-tao","use":0.3137},{"code":"tartaglia","use":0.2964},{"code":"wanderer","use":0.2889},{"code":"ayato","use":0.2357},{"code":"faruzan","use":0.1891},{"code":"ayaka","use":0.1819},{"code":"tighnari","use":0.1543},{"code":"cyno","use":0.1483},{"code":"shenhe","use":0.1429},{"code":"fischl","use":0.1289},{"code":"yaoyao","use":0.1143},{"code":"traveler-anemo","use":0.11},{"code":"itto","use":0.1029},{"code":"kujou-sara","use":0.0949},{"code":"yoimiya","use":0.0908},{"code":"mona","use":0.0897},{"code":"albedo","use":0.0856},{"code":"ganyu","use":0.0789},{"code":"xiao","use":0.0753},{"code":"diona","use":0.0739},{"code":"keqing","use":0.0612},{"code":"venti","use":0.0514},{"code":"eula","use":0.0465},{"code":"layla","use":0.0335},{"code":"barbara","use":0.033},{"code":"gorou","use":0.0315},{"code":"thoma","use":0.0303},{"code":"yun-jin","use":0.0281},{"code":"jean","use":0.027},{"code":"beidou","use":0.0259},{"code":"klee","use":0.0253},{"code":"collei","use":0.0244},{"code":"rosaria","use":0.0189},{"code":"sucrose","use":0.0175},{"code":"qiqi","use":0.0165},{"code":"diluc","use":0.0069},{"code":"noelle","use":0.005},{"code":"yanfei","use":0.004},{"code":"kaeya","use":0.0032},{"code":"lisa","use":0.0025},{"code":"candace","use":0.0021},{"code":"ningguang","use":0.0018},{"code":"sayu","use":0.0018},{"code":"dori","use":0.0018},{"code":"razor","use":0.0014},{"code":"heizou","use":0.0012},{"code":"amber","use":0.0011},{"code":"xinyan","use":0.0011},{"code":"aloy","use":0.001},{"code":"chongyun","use":0.0007}]}